{
  "realm": "kubeatlas",
  "enabled": true,
  "sslRequired": "none",
  "registrationAllowed": false,
  "loginWithEmailAllowed": true,
  "duplicateEmailsAllowed": false,
  "resetPasswordAllowed": true,
  "editUsernameAllowed": false,
  "bruteForceProtected": true,
  "permanentLockout": false,
  "maxFailureWaitSeconds": 900,
  "minimumQuickLoginWaitSeconds": 60,
  "waitIncrementSeconds": 60,
  "quickLoginCheckMilliSeconds": 1000,
  "maxDeltaTimeSeconds": 43200,
  "failureFactor": 30,
  "accessTokenLifespan": 3600,
  "accessTokenLifespanForImplicitFlow": 900,
  "ssoSessionIdleTimeout": 1800,
  "ssoSessionMaxLifespan": 36000,
  "ssoSessionIdleTimeoutRememberMe": 0,
  "ssoSessionMaxLifespanRememberMe": 0,
  "offlineSessionIdleTimeout": 2592000,
  "offlineSessionMaxLifespanEnabled": false,
  "offlineSessionMaxLifespan": 5184000,
  "clientSessionIdleTimeout": 0,
  "clientSessionMaxLifespan": 0,
  "clientOfflineSessionIdleTimeout": 0,
  "clientOfflineSessionMaxLifespan": 0,
  "accessCodeLifespan": 60,
  "accessCodeLifespanUserAction": 300,
  "accessCodeLifespanLogin": 1800,
  "actionTokenGeneratedByAdminLifespan": 43200,
  "actionTokenGeneratedByUserLifespan": 300,
  "oauth2DeviceCodeLifespan": 600,
  "oauth2DevicePollingInterval": 5,
  "refreshTokenMaxReuse": 0,
  "revokeRefreshToken": false,
  "notBefore": 0,
  "defaultSignatureAlgorithm": "RS256",
  "clients": [
    {
      "clientId": "kubeatlas-backend",
      "name": "KubeAtlas Backend",
      "enabled": true,
      "publicClient": false,
      "serviceAccountsEnabled": true,
      "directAccessGrantsEnabled": true,
      "standardFlowEnabled": true,
      "fullScopeAllowed": true,
      "secret": "backend-secret-key",
      "defaultClientScopes": ["roles", "profile", "email"],
      "redirectUris": ["*"],
      "webOrigins": ["*"],
      "attributes": {
        "access.token.lifespan": "3600",
        "client.session.idle.timeout": "1800",
        "client.session.max.lifespan": "36000",
        "client.offline.session.idle.timeout": "2592000",
        "client.offline.session.max.lifespan": "5184000"
      },
      "protocolMappers": [
        {
          "name": "realm roles",
          "protocol": "openid-connect",
          "protocolMapper": "oidc-usermodel-realm-role-mapper",
          "consentRequired": false,
          "config": {
            "multivalued": "true",
            "userinfo.token.claim": "true",
            "id.token.claim": "true",
            "access.token.claim": "true",
            "claim.name": "realm_access.roles",
            "jsonType.label": "String"
          }
        },
        {
          "name": "client roles",
          "protocol": "openid-connect",
          "protocolMapper": "oidc-usermodel-client-role-mapper",
          "consentRequired": false,
          "config": {
            "multivalued": "true",
            "userinfo.token.claim": "true",
            "id.token.claim": "true",
            "access.token.claim": "true",
            "claim.name": "resource_access.${client_id}.roles",
            "jsonType.label": "String"
          }
        }
      ]
    }
  ],
  "roles": {
    "realm": [
      { "name": "admin" },
      { "name": "user" },
      { "name": "guest" }
    ]
  }
  ,
  "users": [
    {
      "username": "admin-service",
      "enabled": true,
      "email": "admin-service@local",
      "firstName": "Admin",
      "lastName": "Service",
      "credentials": [
        { "type": "password", "value": "AdminPassw0rd!", "temporary": false }
      ],
      "realmRoles": ["admin"]
    },
    {
      "username": "service-account-kubeatlas-backend",
      "enabled": true,
      "serviceAccountClientId": "kubeatlas-backend",
      "clientRoles": {
        "realm-management": [
          "manage-users",
          "view-users",
          "query-users",
          "view-realm",
          "manage-realm",
          "view-clients",
          "manage-clients"
        ]
      }
    }
  ]
}


